couchdbkit/__init__.py
couchdbkit/changes.py
couchdbkit/client.py
couchdbkit/exceptions.py
couchdbkit/external.py
couchdbkit/logging.py
couchdbkit/resource.py
couchdbkit/utils.py
couchdbkit/version.py
couchdbkit/consumer/__init__.py
couchdbkit/consumer/base.py
couchdbkit/consumer/ceventlet.py
couchdbkit/consumer/cgevent.py
couchdbkit/consumer/sync.py
couchdbkit/designer/__init__.py
couchdbkit/designer/fs.py
couchdbkit/designer/macros.py
couchdbkit/ext/__init__.py
couchdbkit/ext/django/__init__.py
couchdbkit/ext/django/forms.py
couchdbkit/ext/django/loading.py
couchdbkit/ext/django/schema.py
couchdbkit/ext/django/testrunner.py
couchdbkit/ext/django/management/__init__.py
couchdbkit/ext/django/management/commands/__init__.py
couchdbkit/ext/django/management/commands/sync_couchdb.py
couchdbkit/ext/django/management/commands/sync_finish_couchdb.py
couchdbkit/ext/django/management/commands/sync_prepare_couchdb.py
couchdbkit/schema/__init__.py
couchdbkit/schema/base.py
couchdbkit/schema/properties.py
couchdbkit/schema/properties_proxy.py
couchdbkit/schema/util.py
jsonobject_couchdbkit-1.1.0.dist-info/LICENSE
jsonobject_couchdbkit-1.1.0.dist-info/METADATA
jsonobject_couchdbkit-1.1.0.dist-info/WHEEL
jsonobject_couchdbkit-1.1.0.dist-info/entry_points.txt
jsonobject_couchdbkit-1.1.0.dist-info/top_level.txt
jsonobject_couchdbkit-1.1.0.dist-info/RECORD
