Metadata-Version: 2.1
Name: jsonobject-couchdbkit
Version: 1.1.0
Summary: Python couchdb kit
Home-page: http://couchdbkit.org
Author: Benoit Chesneau
Author-email: benoitc@e-engura.com
License: Apache License 2
Platform: UNKNOWN
Classifier: Development Status :: 4 - Beta
Classifier: Environment :: Other Environment
Classifier: Intended Audience :: Developers
Classifier: License :: OSI Approved :: Apache Software License
Classifier: Operating System :: OS Independent
Classifier: Programming Language :: Python :: 3
Classifier: Programming Language :: Python :: 3.5
Classifier: Programming Language :: Python :: 3.6
Classifier: Programming Language :: Python :: 3.7
Classifier: Programming Language :: Python :: 3 :: Only
Classifier: Topic :: Database
Classifier: Topic :: Utilities
Classifier: Topic :: Software Development :: Libraries :: Python Modules
Provides: couchdbkit
Obsoletes: couchdbkit
License-File: LICENSE
Requires-Dist: jsonobject >=0.9.8
Requires-Dist: cloudant ~=2.7
Requires-Dist: six
